fir_filter.v
module fir_filter(
    input clk,
    input reset,
    input signed [15:0] x_in,
    output reg signed [31:0] y_out
);
    parameter N = 4;

    reg signed [15:0] h [0:N-1];
    reg signed [15:0] shift_reg [0:N-1];
    integer i;

    initial begin
        // Example coefficients: h = [1, 2, 3, 4]
        h[0] = 16'sd1;
        h[1] = 16'sd2;
        h[2] = 16'sd3;
        h[3] = 16'sd4;
    end

    always @(posedge clk or posedge reset) begin
        if (reset) begin
            y_out <= 0;
            for (i = 0; i < N; i = i + 1)
                shift_reg[i] <= 0;
        end else begin
            // Shift input samples
            for (i = N-1; i > 0; i = i - 1)
                shift_reg[i] <= shift_reg[i-1];
            shift_reg[0] <= x_in;

            // Compute FIR output
            y_out <= 0;
            for (i = 0; i < N; i = i + 1)
                y_out <= y_out + shift_reg[i] * h[i];
        end
    end
endmodule

tb_fir_filter.v
`timescale 1ns/1ps
module tb_fir_filter;

    reg clk;
    reg reset;
    reg signed [15:0] x_in;
    wire signed [31:0] y_out;

    fir_filter uut (
        .clk(clk),
        .reset(reset),
        .x_in(x_in),
        .y_out(y_out)
    );

    initial begin
        $dumpfile("fir_wave.vcd");
        $dumpvars(0, tb_fir_filter);

        clk = 0;
        reset = 1;
        x_in = 0;
        #20;
        reset = 0;

        // Apply input samples
        x_in = 16'd1; #10;
        x_in = 16'd2; #10;
        x_in = 16'd3; #10;
        x_in = 16'd4; #10;
        x_in = 16'd5; #10;
        x_in = 16'd6; #10;
        x_in = 16'd7; #10;
        x_in = 16'd8; #10;
        x_in = 16'd0; #100;

        $finish;
    end

    always #5 clk = ~clk;

endmodule

fir_wave.vcd
$date
	Sat May 17 09:08:24 2025
$end
$version
	Icarus Verilog
$end
$timescale
	1ps
$end
$scope module tb_fir_filter $end
$var wire 32 ! y_out [31:0] $end
$var reg 1 " clk $end
$var reg 1 # reset $end
$var reg 16 $ x_in [15:0] $end
$scope module uut $end
$var wire 1 % clk $end
$var wire 1 & reset $end
$var wire 16 ' x_in [15:0] $end
$var integer 32 ( i [31:0] $end
$var reg 32 ) y_out [31:0] $end
$upscope $end
$upscope $end
$enddefinitions $end
#0
$dumpvars
b0 )
b100 (
b0 '
1&
0%
b0 $
1#
0"
b0 !
$end
#5000
b100 (
1"
1%
#10000
0"
0%
#15000
b100 (
1"
1%
#20000
0"
0%
b1 $
b1 '
0#
0&
#25000
b100 (
1"
1%
#30000
0"
0%
b10 $
b10 '
#35000
b0 )
b0 !
b100 (
1"
1%
#40000
0"
0%
b11 $
b11 '
#45000
b0 )
b0 !
b100 (
1"
1%
#50000
0"
0%
b100 $
b100 '
#55000
b0 )
b0 !
b100 (
1"
1%
#60000
0"
0%
b101 $
b101 '
#65000
b100 )
b100 !
b100 (
1"
1%
#70000
0"
0%
b110 $
b110 '
#75000
b1100 )
b1100 !
b100 (
1"
1%
#80000
0"
0%
b111 $
b111 '
#85000
b11000 )
b11000 !
b100 (
1"
1%
#90000
0"
0%
b1000 $
b1000 '
#95000
b101000 )
b101000 !
b100 (
1"
1%
#100000
0"
0%
b0 $
b0 '
#105000
b111100 )
b111100 !
b100 (
1"
1%
#110000
0"
0%
#115000
b1010100 )
b1010100 !
b100 (
1"
1%
#120000
0"
0%
#125000
b1110000 )
b1110000 !
b100 (
1"
1%
#130000
0"
0%
#135000
b10010000 )
b10010000 !
b100 (
1"
1%
#140000
0"
0%
#145000
b10010000 )
b10010000 !
b100 (
1"
1%
#150000
0"
0%
#155000
b10010000 )
b10010000 !
b100 (
1"
1%
#160000
0"
0%
#165000
b10010000 )
b10010000 !
b100 (
1"
1%
#170000
0"
0%
#175000
b10010000 )
b10010000 !
b100 (
1"
1%
#180000
0"
0%
#185000
b10010000 )
b10010000 !
b100 (
1"
1%
#190000
0"
0%
#195000
b10010000 )
b10010000 !
b100 (
1"
1%
